re_name/__init__.py
re_name/__main__.py
re_name/renamer.py
re_name-0.0.23.data/scripts/re_name
re_name-0.0.23.data/scripts/re_name.cmd
re_name-0.0.23.dist-info/LICENSE
re_name-0.0.23.dist-info/METADATA
re_name-0.0.23.dist-info/WHEEL
re_name-0.0.23.dist-info/top_level.txt
re_name-0.0.23.dist-info/RECORD
