Metadata-Version: 2.1
Name: re-name
Version: 0.0.23
Summary: A small example package
Home-page: https://github.com/geforcesong/re_name
Author: George Guo
Author-email: geforcesong@gmail.com
License: UNKNOWN
Platform: UNKNOWN
Classifier: Programming Language :: Python :: 3
Classifier: License :: OSI Approved :: MIT License
Classifier: Operating System :: OS Independent
